LICENSE
README.md
setup.cfg
setup.py
cryptobt/__init__.py
cryptobt/cryptobroker.py
cryptobt/cryptofeed.py
cryptobt/cryptostore.py
cryptobt.egg-info/PKG-INFO
cryptobt.egg-info/SOURCES.txt
cryptobt.egg-info/dependency_links.txt
cryptobt.egg-info/requires.txt
cryptobt.egg-info/top_level.txt