Metadata-Version: 1.0
Name: cryptobt
Version: 1.0.2
Summary: Crypto live data feed and trading support for backtrader
Home-page: https://github.com/bodhion/cryptobt
Author: bodhion
Author-email: crpytobt@bodhion.com
License: MIT
Platform: UNKNOWN
